Metadata-Version: 1.0
Name: distribution-models
Version: 0.1
Summary: some distribution models
Home-page: UNKNOWN
Author: UNKNOWN
Author-email: UNKNOWN
License: UNKNOWN
Platform: UNKNOWN
